c2pa/__init__.py
c2pa/cai_tool.py
c2pa/core.py
c2pa/jumbf.py
c2pa/starling.py
cai/__init__.py
cai/cai_tool.py
cai/core.py
cai/jumbf.py
cai/starling.py
c2pa-1.4.1.dist-info/LICENSE.txt
c2pa-1.4.1.dist-info/METADATA
c2pa-1.4.1.dist-info/WHEEL
c2pa-1.4.1.dist-info/entry_points.txt
c2pa-1.4.1.dist-info/top_level.txt
c2pa-1.4.1.dist-info/RECORD
