Metadata-Version: 2.1
Name: c2pa
Version: 1.4.1
Summary: Implementation of C2PA: Coalition for Content Provenance and Authenticity.
Home-page: https://github.com/numbersprotocol/pyc2pa
Author: Numbers Inc.
Author-email: dev@numbersprotocol.io
License: GPLv3
Keywords: wheels
Platform: UNKNOWN
Classifier: Development Status :: 4 - Beta
Classifier: Intended Audience :: Science/Research
Classifier: Topic :: Scientific/Engineering :: Artificial Intelligence
Classifier: License :: OSI Approved :: GNU General Public License v3 (GPLv3)
Classifier: Programming Language :: Python :: 3
Classifier: Programming Language :: Python :: 3.8
Requires-Python: >=3
License-File: LICENSE.txt
Requires-Dist: py-multibase (>=1.0.3)
Requires-Dist: pycryptodome (>=3.9.9)
Requires-Dist: pymultihash (>=0.8.2)
Requires-Dist: py3exiv2 (>=0.9.3)
Requires-Dist: endesive (>=2.0.2)
